Workbook

Sheet Employees
A1: Employee ID | B1: Full Name | C1: Father Name | D1: Gender | E1: CNIC | F1: Email | G1: Phone | H1: Department | I1: Designation | J1: Basic Salary | K1: Joining Date | L1: Status | M1: Temporary Password | N1: Address | O1: Monthly Salary PKR | P1: Annual Salary PKR | Q1: Education Institute | R1: Education | S1: Date of Birth
A2: EMP-ADM-001 | B2: Bilal Abbasi | C2: Salman Abbasi | D2: Male | E2: 42103-2000157-7 | F2: bilal.abbasi.001@example.com | G2: 0313-6196537 | H2: Admin | I2: System Admin | J2: 68000 | K2: 44936 | L2: Active | M2: Emp@ADM001#01 | N2: Latifabad, Hyderabad | O2: =J2 -> 68000 | P2: =J2*12 -> 816000 | Q2: Institute of Business Administration Karachi | R2: BBA | S2: 30479
A3: EMP-ADM-002 | B3: Salman Baig | C3: Kashif Baig | D3: Male | E3: 42103-2000213-5 | F3: salman.baig.002@example.com | G3: 0333-4834043 | H3: Admin | I3: Admin Officer | J3: 61000 | K3: 44945 | L3: Active | M3: Emp@ADM002#01 | N3: Saddar, Rawalpindi | O3: =J3 -> 61000 | P3: =J3*12 -> 732000 | Q3: Hailey College of Commerce | R3: B.Com | S3: 33200
A4: EMP-ADM-003 | B4: Waqas Yousuf | C4: Faisal Yousuf | D4: Male | E4: 15101-2000269-9 | F4: waqas.yousuf.003@example.com | G4: 0322-3208043 | H4: Admin | I4: Office Coordinator | J4: 54000 | K4: 44954 | L4: Active | M4: Emp@ADM003#01 | N4: North Nazimabad, Karachi | O4: =J4 -> 54000 | P4: =J4*12 -> 648000 | Q4: Adamjee Government Science College | R4: Intermediate | S4: 35526
A5: EMP-ADM-004 | B5: Talha Qureshi | C5: Ehsan Qureshi | D5: Male | E5: 15101-2000325-9 | F5: talha.qureshi.004@example.com | G5: 0301-6852166 | H5: Admin | I5: Records Officer | J5: 78000 | K5: 44963 | L5: Active | M5: Emp@ADM004#01 | N5: Saddar, Rawalpindi | O5: =J5 -> 78000 | P5: =J5*12 -> 936000 | Q5: Federal Urdu University | R5: BS Public Administration | S5: 38247
A6: EMP-ADM-005 | B6: Zeeshan Javed | C6: Bilal Javed | D6: Male | E6: 61101-2000381-1 | F6: zeeshan.javed.005@example.com | G6: 0311-6369157 | H6: Admin | I6: Admin Executive | J6: 62000 | K6: 44972 | L6: Active | M6: Emp@ADM005#01 | N6: Johar Town, Lahore | O6: =J6 -> 62000 | P6: =J6*12 -> 744000 | Q6: University of Karachi Commerce Department | R6: BBA | S6: 30010
A7: EMP-ADM-006 | B7: Moiz Tariq | C7: Shahzaib Tariq | D7: Male | E7: 61101-2000437-9 | F7: moiz.tariq.006@example.com | G7: 0324-2841793 | H7: Admin | I7: System Admin | J7: 89000 | K7: 44981 | L7: Active | M7: Emp@ADM006#01 | N7: G-9, Islamabad | O7: =J7 -> 89000 | P7: =J7*12 -> 1068000 | Q7: Hailey College of Commerce | R7: B.Com | S7: 32700
A8: EMP-ADM-007 | B8: Mustafa Zafar | C8: Haroon Zafar | D8: Male | E8: 35202-2000493-9 | F8: mustafa.zafar.007@example.com | G8: 0311-7796852 | H8: Admin | I8: Admin Officer | J8: 85000 | K8: 44990 | L8: Active | M8: Emp@ADM007#01 | N8: Saddar, Rawalpindi | O8: =J8 -> 85000 | P8: =J8*12 -> 1020000 | Q8: DJ Sindh Government Science College | R8: Intermediate | S8: 35421
A9: EMP-ADM-008 | B9: Hussain Mirza | C9: Sufyan Mirza | D9: Male | E9: 42201-2000549-3 | F9: hussain.mirza.008@example.com | G9: 0303-8185229 | H9: Admin | I9: Office Coordinator | J9: 59000 | K9: 44999 | L9: Active | M9: Emp@ADM008#01 | N9: Gulshan-e-Iqbal, Karachi | O9: =J9 -> 59000 | P9: =J9*12 -> 708000 | Q9: Federal Urdu University | R9: BS Public Administration | S9: 37746
A10: EMP-ADM-009 | B10: Fahad Niazi | C10: Ahmed Niazi | D10: Male | E10: 42201-2000605-3 | F10: fahad.niazi.009@example.com | G10: 0315-6226005 | H10: Admin | I10: Records Officer | J10: 62000 | K10: 45008 | L10: Active | M10: Emp@ADM009#01 | N10: Model Town, Lahore | O10: =J10 -> 62000 | P10: =J10*12 -> 744000 | Q10: Bahria University Business Department | R10: BBA | S10: 29875
A11: EMP-ADM-010 | B11: Rizwan Nadeem | C11: Farhan Nadeem | D11: Male | E11: 35202-2000661-3 | F11: rizwan.nadeem.010@example.com | G11: 0321-3004095 | H11: Admin | I11: Admin Executive | J11: 87000 | K11: 45017 | L11: Active | M11: Emp@ADM010#01 | N11: G-9, Islamabad | O11: =J11 -> 87000 | P11: =J11*12 -> 1044000 | Q11: Hailey College of Commerce | R11: B.Com | S11: 32229
A12: EMP-ADM-011 | B12: Junaid Ali | C12: Asim Ali | D12: Male | E12: 42102-2000717-3 | F12: junaid.ali.011@example.com | G12: 0302-5113754 | H12: Admin | I12: System Admin | J12: 87000 | K12: 45026 | L12: Active | M12: Emp@ADM011#01 | N12: Gulshan-e-Iqbal, Karachi | O12: =J12 -> 87000 | P12: =J12*12 -> 1044000 | Q12: Superior College | R12: Intermediate | S12: 34921
A13: EMP-ADM-012 | B13: Rayyan Hashmi | C13: Shayan Hashmi | D13: Male | E13: 37405-2000773-9 | F13: rayyan.hashmi.012@example.com | G13: 0311-1802719 | H13: Admin | I13: Admin Officer | J13: 75000 | K13: 45035 | L13: Active | M13: Emp@ADM012#01 | N13: Model Town, Lahore | O13: =J13 -> 75000 | P13: =J13*12 -> 900000 | Q13: Federal Urdu University | R13: BS Public Administration | S13: 37277
... A451: EMP-OPS-025 | B451: Ehsan Butt | C451: Sameer Butt | D451: Male | E451: 42103-2018943-1 | F451: ehsan.butt.450@example.com | G451: 0324-6945058 | H451: Operations | I451: Operations Analyst | J451: 76000 | K451: 45497 | L451: Active | M451: Emp@OPS025#18 | N451: G-9, Islamabad | O451: =J451 -> 76000 | P451: =J451*12 -> 912000 | Q451: TEVTA Training Institute | R451: MBA Operations | S451: 34538

Sheet Departments
A1: Department | B1: Code | C1: Employees Required | D1: Current Employees | E1: Active Employees | F1: Inactive Employees | G1: Total Payroll | H1: Average Salary
A2: Admin | B2: ADM | C2: 25 | D2: =COUNTIF(Employees!$H:$H,A2) -> 25 | E2: =COUNTIFS(Employees!$H:$H,A2,Employees!$L:$L,"Active") -> 23 | F2: =COUNTIFS(Employees!$H:$H,A2,Employees!$L:$L,"Inactive") -> 2 | G2: =SUMIF(Employees!$H:$H,A2,Employees!$J:$J) -> 1786000 | H2: =IFERROR(G2/D2,0) -> 71440
A3: Management | B3: MGT | C3: 25 | D3: =COUNTIF(Employees!$H:$H,A3) -> 25 | E3: =COUNTIFS(Employees!$H:$H,A3,Employees!$L:$L,"Active") -> 23 | F3: =COUNTIFS(Employees!$H:$H,A3,Employees!$L:$L,"Inactive") -> 2 | G3: =SUMIF(Employees!$H:$H,A3,Employees!$J:$J) -> 3583000 | H3: =IFERROR(G3/D3,0) -> 143320
A4: Sales | B4: SAL | C4: 25 | D4: =COUNTIF(Employees!$H:$H,A4) -> 25 | E4: =COUNTIFS(Employees!$H:$H,A4,Employees!$L:$L,"Active") -> 25 | F4: =COUNTIFS(Employees!$H:$H,A4,Employees!$L:$L,"Inactive") -> 0 | G4: =SUMIF(Employees!$H:$H,A4,Employees!$J:$J) -> 1884000 | H4: =IFERROR(G4/D4,0) -> 75360
A5: Purchase | B5: PUR | C5: 25 | D5: =COUNTIF(Employees!$H:$H,A5) -> 25 | E5: =COUNTIFS(Employees!$H:$H,A5,Employees!$L:$L,"Active") -> 24 | F5: =COUNTIFS(Employees!$H:$H,A5,Employees!$L:$L,"Inactive") -> 1 | G5: =SUMIF(Employees!$H:$H,A5,Employees!$J:$J) -> 2059000 | H5: =IFERROR(G5/D5,0) -> 82360
A6: Inventory | B6: INV | C6: 25 | D6: =COUNTIF(Employees!$H:$H,A6) -> 25 | E6: =COUNTIFS(Employees!$H:$H,A6,Employees!$L:$L,"Active") -> 23 | F6: =COUNTIFS(Employees!$H:$H,A6,Employees!$L:$L,"Inactive") -> 2 | G6: =SUMIF(Employees!$H:$H,A6,Employees!$J:$J) -> 1828000 | H6: =IFERROR(G6/D6,0) -> 73120
A7: Warehouse | B7: WH | C7: 25 | D7: =COUNTIF(Employees!$H:$H,A7) -> 25 | E7: =COUNTIFS(Employees!$H:$H,A7,Employees!$L:$L,"Active") -> 23 | F7: =COUNTIFS(Employees!$H:$H,A7,Employees!$L:$L,"Inactive") -> 2 | G7: =SUMIF(Employees!$H:$H,A7,Employees!$J:$J) -> 1368000 | H7: =IFERROR(G7/D7,0) -> 54720
A8: Logistics | B8: LOG | C8: 25 | D8: =COUNTIF(Employees!$H:$H,A8) -> 25 | E8: =COUNTIFS(Employees!$H:$H,A8,Employees!$L:$L,"Active") -> 24 | F8: =COUNTIFS(Employees!$H:$H,A8,Employees!$L:$L,"Inactive") -> 1 | G8: =SUMIF(Employees!$H:$H,A8,Employees!$J:$J) -> 1920000 | H8: =IFERROR(G8/D8,0) -> 76800
A9: Delivery | B9: DEL | C9: 25 | D9: =COUNTIF(Employees!$H:$H,A9) -> 25 | E9: =COUNTIFS(Employees!$H:$H,A9,Employees!$L:$L,"Active") -> 24 | F9: =COUNTIFS(Employees!$H:$H,A9,Employees!$L:$L,"Inactive") -> 1 | G9: =SUMIF(Employees!$H:$H,A9,Employees!$J:$J) -> 1179000 | H9: =IFERROR(G9/D9,0) -> 47160
A10: Customer Support | B10: CS | C10: 25 | D10: =COUNTIF(Employees!$H:$H,A10) -> 25 | E10: =COUNTIFS(Employees!$H:$H,A10,Employees!$L:$L,"Active") -> 22 | F10: =COUNTIFS(Employees!$H:$H,A10,Employees!$L:$L,"Inactive") -> 3 | G10: =SUMIF(Employees!$H:$H,A10,Employees!$J:$J) -> 1446000 | H10: =IFERROR(G10/D10,0) -> 57840
A11: Accounts | B11: ACC | C11: 25 | D11: =COUNTIF(Employees!$H:$H,A11) -> 25 | E11: =COUNTIFS(Employees!$H:$H,A11,Employees!$L:$L,"Active") -> 25 | F11: =COUNTIFS(Employees!$H:$H,A11,Employees!$L:$L,"Inactive") -> 0 | G11: =SUMIF(Employees!$H:$H,A11,Employees!$J:$J) -> 2055000 | H11: =IFERROR(G11/D11,0) -> 82200
A12: Finance | B12: FIN | C12: 25 | D12: =COUNTIF(Employees!$H:$H,A12) -> 25 | E12: =COUNTIFS(Employees!$H:$H,A12,Employees!$L:$L,"Active") -> 23 | F12: =COUNTIFS(Employees!$H:$H,A12,Employees!$L:$L,"Inactive") -> 2 | G12: =SUMIF(Employees!$H:$H,A12,Employees!$J:$J) -> 2764000 | H12: =IFERROR(G12/D12,0) -> 110560
A13: Marketing | B13: MKT | C13: 25 | D13: =COUNTIF(Employees!$H:$H,A13) -> 25 | E13: =COUNTIFS(Employees!$H:$H,A13,Employees!$L:$L,"Active") -> 22 | F13: =COUNTIFS(Employees!$H:$H,A13,Employees!$L:$L,"Inactive") -> 3 | G13: =SUMIF(Employees!$H:$H,A13,Employees!$J:$J) -> 2454000 | H13: =IFERROR(G13/D13,0) -> 98160
... A19: Operations | B19: OPS | C19: 25 | D19: =COUNTIF(Employees!$H:$H,A19) -> 25 | E19: =COUNTIFS(Employees!$H:$H,A19,Employees!$L:$L,"Active") -> 23 | F19: =COUNTIFS(Employees!$H:$H,A19,Employees!$L:$L,"Inactive") -> 2 | G19: =SUMIF(Employees!$H:$H,A19,Employees!$J:$J) -> 2203000 | H19: =IFERROR(G19/D19,0) -> 88120

Sheet Summary
A1: E-Commerce Male Employees Dataset
A2: Metric | B2: Value | C2: Formula / Detail
A3: Total Departments | B3: 18 | C3: 18 departments
A4: Employees Per Department | B4: 25 | C4: Fixed requirement
A5: Total Employees | B5: =COUNTA(Employees!A2:A451) -> 450 | C5: =COUNTA(Employees!A2:A451) -> 450
A6: Male Employees | B6: =COUNTIF(Employees!D:D,"Male") -> 450 | C6: =COUNTIF(Employees!D:D,"Male") -> 450
A7: Active Employees | B7: =COUNTIF(Employees!L:L,"Active") -> 423 | C7: =COUNTIF(Employees!L:L,"Active") -> 423
A8: Total Monthly Payroll | B8: =SUM(Employees!J:J) -> 37523000 | C8: =SUM(Employees!J:J) -> 37523000
A9: Average Salary | B9: =AVERAGE(Employees!J:J) -> 83384.444 | C9: =AVERAGE(Employees!J:J) -> 83384.444
A12: Department | B12: Employee Count
A13: Admin | B13: 25
A14: Management | B14: 25
A15: Sales | B15: 25
A16: Purchase | B16: 25
A17: Inventory | B17: 25
A18: Warehouse | B18: 25
A19: Logistics | B19: 25
A20: Delivery | B20: 25
A21: Customer Support | B21: 25
A22: Accounts | B22: 25
A23: Finance | B23: 25
A24: Marketing | B24: 25
... A30: Operations | B30: 25

Sheet Laravel Import Notes
A1: Laravel Import Notes
A2: 1 | B2: All rows are sample/fake male employee records for testing and seeding.
A3: 2 | B3: CNIC values are dummy Pakistani-format values. Do not use them as real identity data.
A4: 3 | B4: Temporary Password column is plain text only for import/demo. In Laravel, always save passwords with Hash::make($password).
A5: 4 | B5: Suggested columns for employees table: employee_code, name, father_name, gender, cnic, email, phone, department_id, designation, salary, joining_date, status.
A6: 5 | B6: Create department records first, then map employees by Department name or Code.
A7: Example | B7: User::create(['name'=>$row['Full Name'], 'email'=>$row['Email'], 'password'=>Hash::make($row['Temporary Password'])]);
A8: 6 | B8: Column Q has been changed from Organization to Education Institute. Use this for the employee's educational organization/institute.
A9: 7 | B9: Suggested updated employees columns: employee_code, name, father_name, gender, cnic, email, phone, department_id, designation, salary, joining_date, date_of_birth, status, education_institute, education.
A10: 8 | B10: For user login imports, create users first and hash Temporary Password using Hash::make($row['Temporary Password']).
A11: 9 | B11: Added Date of Birth column as date_of_birth for Laravel employee import.

Sheet Organizations
A1: Education Institute Summary
A3: Education Institute | B3: Degrees / Certificates Covered | C3: Employee Count
A4: ACCA Pakistan Learning Partner | B4: ACCA | C4: =COUNTIF(Employees!$Q$2:$Q$451,A4) -> 6
A5: Adamjee Government Science College | B5: Intermediate, Matric | C5: =COUNTIF(Employees!$Q$2:$Q$451,A5) -> 20
A6: Bahria University Business Department | B6: BA, BBA, BBA Finance, BBA HRM, BBA Marketing, BS Business Administration, Diploma in QA, MBA, MBA Finance, MBA HRM, MBA Marketing, MS Management | C6: =COUNTIF(Employees!$Q$2:$Q$451,A6) -> 27
A7: COMSATS University | B7: Diploma in IT | C7: =COUNTIF(Employees!$Q$2:$Q$451,A7) -> 7
A8: DJ Sindh Government Science College | B8: Intermediate, Matric | C8: =COUNTIF(Employees!$Q$2:$Q$451,A8) -> 18
A9: FAST NUCES | B9: BS Computer Science, BS Quality Management | C9: =COUNTIF(Employees!$Q$2:$Q$451,A9) -> 12
A10: Federal Urdu University | B10: BS Public Administration | C10: =COUNTIF(Employees!$Q$2:$Q$451,A10) -> 6
A11: Government College of Commerce Karachi | B11: B.Com, M.Com | C11: =COUNTIF(Employees!$Q$2:$Q$451,A11) -> 33
A12: Government Degree College Gulshan-e-Iqbal | B12: Intermediate, Matric | C12: =COUNTIF(Employees!$Q$2:$Q$451,A12) -> 21
A13: Hailey College of Commerce | B13: B.Com | C13: =COUNTIF(Employees!$Q$2:$Q$451,A13) -> 12
A14: Institute of Business Administration Karachi | B14: BA, BBA, BBA Finance, BBA HRM, BBA Marketing, BS Business Administration, Diploma in QA, MBA, MBA Finance, MBA HRM, MBA Marketing, MS Management | C14: =COUNTIF(Employees!$Q$2:$Q$451,A14) -> 29
A15: Institute of Logistics & Supply Chain Management | B15: BBA Operations, BBA Supply Chain, Diploma in Driving / Delivery Operations, Diploma in Logistics | C15: =COUNTIF(Employees!$Q$2:$Q$451,A15) -> 26
... A32: Virtual University Commerce Program | B32: B.Com | C32: =COUNTIF(Employees!$Q$2:$Q$451,A32) -> 12

Sheet Education Summary
A1: Education Summary
A3: Education | B3: Employee Count
A4: ACCA | B4: =COUNTIF(Employees!$R:$R,A4) -> 6
A5: ACCA Foundation | B5: =COUNTIF(Employees!$R:$R,A5) -> 6
A6: B.Com | B6: =COUNTIF(Employees!$R:$R,A6) -> 50
A7: BA | B7: =COUNTIF(Employees!$R:$R,A7) -> 18
A8: BBA | B8: =COUNTIF(Employees!$R:$R,A8) -> 26
A9: BBA Finance | B9: =COUNTIF(Employees!$R:$R,A9) -> 6
A10: BBA HRM | B10: =COUNTIF(Employees!$R:$R,A10) -> 7
A11: BBA Marketing | B11: =COUNTIF(Employees!$R:$R,A11) -> 12
A12: BBA Operations | B12: =COUNTIF(Employees!$R:$R,A12) -> 6
A13: BBA Supply Chain | B13: =COUNTIF(Employees!$R:$R,A13) -> 18
A14: BS Business Administration | B14: =COUNTIF(Employees!$R:$R,A14) -> 12
A15: BS Computer Science | B15: =COUNTIF(Employees!$R:$R,A15) -> 12
... A39: Matric | B39: =COUNTIF(Employees!$R:$R,A39) -> 14
